{
    "Aoe": {
        "Defense": 1.2,
        "Attack": 0.9,
        "Aoe": 1.0,
        "Support": 1.0,
        "Curse": 1.0,
        "Cure": 1.0,
        "Summon": 1.0
    },
    "Curse": {
        "Defense": 1.05,
        "Attack": 1.05,
        "Aoe": 1.05,
        "Support": 1.2,
        "Curse": 1.0,
        "Cure": 1.05,
        "Summon": 1.05
    },
    "Support": {
        "Defense": 1.05,
        "Attack": 1.05,
        "Aoe": 1.05,
        "Support": 1.0,
        "Curse": 1.2,
        "Cure": 1.05,
        "Summon": 1.05
    },
    "Summon": {
        "Defense": 1.0,
        "Attack": 1.0,
        "Aoe": 1.0,
        "Support": 1.0,
        "Curse": 1.0,
        "Cure": 1.0,
        "Summon": 1.0
    },
    "Attack": {
        "Defense": 0.9,
        "Attack": 1.0,
        "Aoe": 1.2,
        "Support": 1.0,
        "Curse": 1.0,
        "Cure": 1.0,
        "Summon": 1.0
    },
    "Defense": {
        "Defense": 1.0,
        "Attack": 1.2,
        "Aoe": 0.9,
        "Support": 1.0,
        "Curse": 1.0,
        "Cure": 1.0,
        "Summon": 1.0
    },
    "Cure": {
        "Defense": 1.0,
        "Attack": 1.0,
        "Aoe": 1.0,
        "Support": 1.0,
        "Curse": 1.0,
        "Cure": 1.0,
        "Summon": 1.0
    }
}