{
    "BSNCT_01": {
        "ClueList": [
            "BSNCT_01_C1",
            "BSNCT_01_C2",
            "BSNCT_01_C3",
            "BSNCT_01_C4",
            "BSNCT_01_C5",
            "BSNCT_01_C6",
            "BSNCT_01_C7",
            "BSNCT_01_C8",
            "BSNCT_01_C9",
            "BSNCT_01_C10",
            "BSNCT_01_C11",
            "BSNCT_01_C12",
            "BSNCT_01_C13",
            "BSNCT_01_C14",
            "BSNCT_01_C15",
            "BSNCT_01_C16",
            "BSNCT_01_C17",
            "BSNCT_01_C18",
            "BSNCT_01_C19",
            "BSNCT_01_C20",
            "BSNCT_01_C21",
            "BSNCT_01_C22",
            "BSNCT_01_C23",
            "BSNCT_01_C24",
            "BSNCT_01_C25",
            "BSNCT_01_C26",
            "BSNCT_01_C27",
            "BSNCT_01_C28",
            "BSNCT_01_C29",
            "BSNCT_01_C30",
            "BSNCT_01_C31",
            "BSNCT_01_C32",
            "BSNCT_01_C33",
            "BSNCT_01_C34",
            "BSNCT_01_C35",
            "BSNCT_01_C36",
            "BSNCT_01_C37",
            "BSNCT_01_C38",
            "BSNCT_01_C39",
            "BSNCT_01_C40",
            "BSNCT_01_C41",
            "BSNCT_01_C42",
            "BSNCT_01_C43",
            "BSNCT_01_C44",
            "BSNCT_01_C45",
            "BSNCT_01_C46",
            "BSNCT_01_C47",
            "BSNCT_01_C48",
            "BSNCT_01_C49",
            "BSNCT_01_C50",
            "BSNCT_01_C51",
            "BSNCT_01_C52",
            "BSNCT_01_C53",
            "BSNCT_01_C54",
            "BSNCT_01_C55",
            "BSNCT_01_C56",
            "BSNCT_01_C57",
            "BSNCT_01_C58",
            "BSNCT_01_C59",
            "BSNCT_01_C60",
            "BSNCT_01_C61",
            "BSNCT_01_C62",
            "BSNCT_01_C63",
            "BSNCT_01_C64",
            "BSNCT_01_C65",
            "BSNCT_01_C66",
            "BSNCT_01_C67",
            "BSNCT_01_C68",
            "BSNCT_01_C69",
            "BSNCT_01_C70",
            "BSNCT_01_C71",
            "BSNCT_01_C72",
            "BSNCT_01_C73",
            "BSNCT_01_C74",
            "BSNCT_01_C75",
            "BSNCT_01_C76",
            "BSNCT_01_C77",
            "BSNCT_01_C78",
            "BSNCT_01_C79",
            "BSNCT_01_C80",
            "BSNCT_01_C81",
            "BSNCT_01_C82",
            "BSNCT_01_C83",
            "BSNCT_01_C84",
            "BSNCT_01_C85",
            "BSNCT_01_C86",
            "BSNCT_01_C87",
            "BSNCT_01_C88",
            "BSNCT_01_C89",
            "BSNCT_01_C90",
            "BSNCT_01_C91",
            "BSNCT_01_C92",
            "BSNCT_01_C93",
            "BSNCT_01_C94",
            "BSNCT_01_C95",
            "BSNCT_01_C96",
            "BSNCT_01_C97",
            "BSNCT_01_C98",
            "BSNCT_01_C99",
            "BSNCT_01_C100",
            "BSNCT_01_C101",
            "BSNCT_01_C102",
            "BSNCT_01_C103",
            "BSNCT_01_C104",
            "BSNCT_01_C105",
            "BSNCT_01_C106",
            "BSNCT_01_C107",
            "BSNCT_01_C108",
            "BSNCT_01_C109",
            "BSNCT_01_C110"
        ],
        "DPReward": {
            "120": "exp_small",
            "30": "exp_small",
            "60": "exp_small",
            "90": "exp_small"
        },
        "DPTask": [
            "BSNCT_01_DP1",
            "BSNCT_01_DP2",
            "BSNCT_01_DP3",
            "BSNCT_01_DP4",
            "BSNCT_01_DP5",
            "BSNCT_01_DP6",
            "BSNCT_01_DP7",
            "BSNCT_01_DP8",
            "BSNCT_01_DP9",
            "BSNCT_01_DP10",
            "BSNCT_01_DP11",
            "BSNCT_01_DP12",
            "BSNCT_01_DP13",
            "BSNCT_01_DP14"
        ],
        "EliteData": {
            "chapter": "N_A",
            "initGold": 20,
            "value": "N1"
        },
        "EliteUnlock": [
            "BSNCT_01_S1",
            "BSNCT_01_S2",
            "BSNCT_01_S3",
            "BSNCT_01_S4",
            "BSNCT_01_S5",
            "BSNCT_01_S6",
            "BSNCT_01_S7",
            "BSNCT_01_S8"
        ],
        "InfData": "",
        "InfUnlock": "",
        "InitAttr": "P_Master_Lv1",
        "InitHero": {
            "ALSi": "P_Hero_Lv1",
            "GLin": "P_Hero_Lv1",
            "XLai": "P_Hero_Lv1",
            "YKDMLai": "P_Hero_Lv1"
        },
        "Master": "PansLab_Master_LieSha",
        "NormalData": {
            "chapter": "N_A",
            "initGold": 20,
            "value": "N1"
        },
        "NormalUnlock": {
            "level": 1
        },
        "Picture": "",
        "Position": 1,
        "SpecialSkill": {
            "cd": 3,
            "desc": "PansLab_BSNCT_01_SpecialSkill",
            "skill": "HeroUp"
        },
        "StoryName": "BSNCT_01_Name",
        "TalentChange": 12,
        "TalentList": [
            "BSNCT_01_Talent1",
            "BSNCT_01_Talent2",
            "BSNCT_01_Talent3",
            "BSNCT_01_Talent4",
            "BSNCT_01_Talent5",
            "BSNCT_01_Talent6",
            "BSNCT_01_Talent7",
            "BSNCT_01_Talent8",
            "BSNCT_01_Talent9",
            "BSNCT_01_Talent10"
        ],
        "TeamBuff": {
            "attr": [
                "PansLab_TeamBuff_1",
                "PansLab_TeamBuff_2",
                "PansLab_TeamBuff_3",
                "PansLab_TeamBuff_4",
                "PansLab_TeamBuff_5"
            ],
            "level": [
                1,
                2,
                3,
                4,
                5,
                6,
                7,
                8,
                9,
                10
            ],
            "special": []
        }
    },
    "BSNCT_02": {
        "ClueList": [
            "BSNCT_01_C1",
            "BSNCT_01_C2",
            "BSNCT_01_C3",
            "BSNCT_01_C4",
            "BSNCT_01_C5",
            "BSNCT_01_C6",
            "BSNCT_01_C7",
            "BSNCT_01_C8",
            "BSNCT_01_C9",
            "BSNCT_01_C10",
            "BSNCT_01_C11",
            "BSNCT_01_C12",
            "BSNCT_01_C13",
            "BSNCT_01_C14",
            "BSNCT_01_C15",
            "BSNCT_01_C16",
            "BSNCT_01_C17",
            "BSNCT_01_C18",
            "BSNCT_01_C19",
            "BSNCT_01_C20",
            "BSNCT_01_C21",
            "BSNCT_01_C22",
            "BSNCT_01_C23",
            "BSNCT_01_C24",
            "BSNCT_01_C25",
            "BSNCT_01_C26",
            "BSNCT_01_C27",
            "BSNCT_01_C28",
            "BSNCT_01_C29",
            "BSNCT_01_C30",
            "BSNCT_01_C31",
            "BSNCT_01_C32",
            "BSNCT_01_C33",
            "BSNCT_01_C34",
            "BSNCT_01_C35",
            "BSNCT_01_C36",
            "BSNCT_01_C37",
            "BSNCT_01_C38",
            "BSNCT_01_C39",
            "BSNCT_01_C40",
            "BSNCT_01_C41",
            "BSNCT_01_C42",
            "BSNCT_01_C43",
            "BSNCT_01_C44",
            "BSNCT_01_C45",
            "BSNCT_01_C46",
            "BSNCT_01_C47",
            "BSNCT_01_C48",
            "BSNCT_01_C49",
            "BSNCT_01_C50",
            "BSNCT_01_C51",
            "BSNCT_01_C52",
            "BSNCT_01_C53",
            "BSNCT_01_C54",
            "BSNCT_01_C55",
            "BSNCT_01_C56",
            "BSNCT_01_C57",
            "BSNCT_01_C58",
            "BSNCT_01_C59",
            "BSNCT_01_C60",
            "BSNCT_01_C61",
            "BSNCT_01_C62",
            "BSNCT_01_C63",
            "BSNCT_01_C64",
            "BSNCT_01_C65",
            "BSNCT_01_C66",
            "BSNCT_01_C67",
            "BSNCT_01_C68",
            "BSNCT_01_C69",
            "BSNCT_01_C70",
            "BSNCT_01_C71",
            "BSNCT_01_C72",
            "BSNCT_01_C73",
            "BSNCT_01_C74",
            "BSNCT_01_C75",
            "BSNCT_01_C76",
            "BSNCT_01_C77",
            "BSNCT_01_C78",
            "BSNCT_01_C79",
            "BSNCT_01_C80",
            "BSNCT_01_C81",
            "BSNCT_01_C82",
            "BSNCT_01_C83",
            "BSNCT_01_C84",
            "BSNCT_01_C85",
            "BSNCT_01_C86",
            "BSNCT_01_C87",
            "BSNCT_01_C88",
            "BSNCT_01_C89",
            "BSNCT_01_C90",
            "BSNCT_01_C91",
            "BSNCT_01_C92",
            "BSNCT_01_C93",
            "BSNCT_01_C94",
            "BSNCT_01_C95",
            "BSNCT_01_C96",
            "BSNCT_01_C97",
            "BSNCT_01_C98",
            "BSNCT_01_C99",
            "BSNCT_01_C100",
            "BSNCT_01_C101",
            "BSNCT_01_C102",
            "BSNCT_01_C103",
            "BSNCT_01_C104",
            "BSNCT_01_C105",
            "BSNCT_01_C106",
            "BSNCT_01_C107",
            "BSNCT_01_C108",
            "BSNCT_01_C109",
            "BSNCT_01_C110",
            "BSNCT_01_C111",
            "BSNCT_01_C112",
            "BSNCT_01_C113",
            "BSNCT_01_C114",
            "BSNCT_01_C115",
            "BSNCT_01_C116",
            "BSNCT_01_C117",
            "BSNCT_01_C118",
            "BSNCT_01_C119",
            "BSNCT_01_C120"
        ],
        "DPReward": {
            "120": "exp_small",
            "30": "exp_small",
            "60": "exp_small",
            "90": "exp_small"
        },
        "DPTask": [
            "BSNCT_01_DP1",
            "BSNCT_01_DP2",
            "BSNCT_01_DP3",
            "BSNCT_01_DP4",
            "BSNCT_01_DP5",
            "BSNCT_01_DP6",
            "BSNCT_01_DP7",
            "BSNCT_01_DP8",
            "BSNCT_01_DP9",
            "BSNCT_01_DP10",
            "BSNCT_01_DP11",
            "BSNCT_01_DP12",
            "BSNCT_01_DP13",
            "BSNCT_01_DP14"
        ],
        "EliteData": {
            "chapter": "N_A",
            "initGold": 50,
            "value": "N1"
        },
        "EliteUnlock": [
            "BSNCT_01_S2"
        ],
        "InfData": "",
        "InfUnlock": "",
        "InitAttr": "P_Master_Lv1",
        "InitHero": {
            "HLDNan": "P_Hero_Lv1",
            "JDCZhang": "P_Hero_Lv1",
            "YFZZhu": "P_Hero_Lv1"
        },
        "Master": "PansLab_Player_DFQi",
        "NormalData": {
            "chapter": "N_A",
            "initGold": 50,
            "value": "N1"
        },
        "NormalUnlock": {
            "level": 999
        },
        "Picture": "",
        "Position": 2,
        "SpecialSkill": {
            "cd": 3,
            "desc": "PansLab_BSNCT_01_SpecialSkill",
            "skill": "HeroUp"
        },
        "StoryName": "BSNCT_01_Name",
        "TalentChange": 12,
        "TalentList": [
            "BSNCT_01_Talent1",
            "BSNCT_01_Talent2",
            "BSNCT_01_Talent3",
            "BSNCT_01_Talent4",
            "BSNCT_01_Talent5",
            "BSNCT_01_Talent6",
            "BSNCT_01_Talent7",
            "BSNCT_01_Talent8",
            "BSNCT_01_Talent9",
            "BSNCT_01_Talent10"
        ],
        "TeamBuff": {
            "attr": [
                "PansLab_TeamBuff_1",
                "PansLab_TeamBuff_2",
                "PansLab_TeamBuff_3",
                "PansLab_TeamBuff_4",
                "PansLab_TeamBuff_5"
            ],
            "level": [
                2,
                4,
                6,
                8,
                10
            ],
            "special": []
        }
    },
    "BSNCT_03": {
        "ClueList": [
            "BSNCT_01_C1",
            "BSNCT_01_C2",
            "BSNCT_01_C3",
            "BSNCT_01_C4",
            "BSNCT_01_C5",
            "BSNCT_01_C6",
            "BSNCT_01_C7",
            "BSNCT_01_C8",
            "BSNCT_01_C9",
            "BSNCT_01_C10",
            "BSNCT_01_C11",
            "BSNCT_01_C12",
            "BSNCT_01_C13",
            "BSNCT_01_C14",
            "BSNCT_01_C15",
            "BSNCT_01_C16",
            "BSNCT_01_C17",
            "BSNCT_01_C18",
            "BSNCT_01_C19",
            "BSNCT_01_C20",
            "BSNCT_01_C21",
            "BSNCT_01_C22",
            "BSNCT_01_C23",
            "BSNCT_01_C24",
            "BSNCT_01_C25",
            "BSNCT_01_C26",
            "BSNCT_01_C27",
            "BSNCT_01_C28",
            "BSNCT_01_C29",
            "BSNCT_01_C30",
            "BSNCT_01_C31",
            "BSNCT_01_C32",
            "BSNCT_01_C33",
            "BSNCT_01_C34",
            "BSNCT_01_C35",
            "BSNCT_01_C36",
            "BSNCT_01_C37",
            "BSNCT_01_C38",
            "BSNCT_01_C39",
            "BSNCT_01_C40",
            "BSNCT_01_C41",
            "BSNCT_01_C42",
            "BSNCT_01_C43",
            "BSNCT_01_C44",
            "BSNCT_01_C45",
            "BSNCT_01_C46",
            "BSNCT_01_C47",
            "BSNCT_01_C48",
            "BSNCT_01_C49",
            "BSNCT_01_C50",
            "BSNCT_01_C51",
            "BSNCT_01_C52",
            "BSNCT_01_C53",
            "BSNCT_01_C54",
            "BSNCT_01_C55",
            "BSNCT_01_C56",
            "BSNCT_01_C57",
            "BSNCT_01_C58",
            "BSNCT_01_C59",
            "BSNCT_01_C60",
            "BSNCT_01_C61",
            "BSNCT_01_C62",
            "BSNCT_01_C63",
            "BSNCT_01_C64",
            "BSNCT_01_C65",
            "BSNCT_01_C66",
            "BSNCT_01_C67",
            "BSNCT_01_C68",
            "BSNCT_01_C69",
            "BSNCT_01_C70",
            "BSNCT_01_C71",
            "BSNCT_01_C72",
            "BSNCT_01_C73",
            "BSNCT_01_C74",
            "BSNCT_01_C75",
            "BSNCT_01_C76",
            "BSNCT_01_C77",
            "BSNCT_01_C78",
            "BSNCT_01_C79",
            "BSNCT_01_C80",
            "BSNCT_01_C81",
            "BSNCT_01_C82",
            "BSNCT_01_C83",
            "BSNCT_01_C84",
            "BSNCT_01_C85",
            "BSNCT_01_C86",
            "BSNCT_01_C87",
            "BSNCT_01_C88",
            "BSNCT_01_C89",
            "BSNCT_01_C90",
            "BSNCT_01_C91",
            "BSNCT_01_C92",
            "BSNCT_01_C93",
            "BSNCT_01_C94",
            "BSNCT_01_C95",
            "BSNCT_01_C96",
            "BSNCT_01_C97",
            "BSNCT_01_C98",
            "BSNCT_01_C99",
            "BSNCT_01_C100",
            "BSNCT_01_C101",
            "BSNCT_01_C102",
            "BSNCT_01_C103",
            "BSNCT_01_C104",
            "BSNCT_01_C105",
            "BSNCT_01_C106",
            "BSNCT_01_C107",
            "BSNCT_01_C108",
            "BSNCT_01_C109",
            "BSNCT_01_C110",
            "BSNCT_01_C111",
            "BSNCT_01_C112",
            "BSNCT_01_C113",
            "BSNCT_01_C114",
            "BSNCT_01_C115",
            "BSNCT_01_C116",
            "BSNCT_01_C117",
            "BSNCT_01_C118",
            "BSNCT_01_C119",
            "BSNCT_01_C120"
        ],
        "DPReward": {
            "120": "exp_small",
            "30": "exp_small",
            "60": "exp_small",
            "90": "exp_small"
        },
        "DPTask": [
            "BSNCT_01_DP1",
            "BSNCT_01_DP2",
            "BSNCT_01_DP3",
            "BSNCT_01_DP4",
            "BSNCT_01_DP5",
            "BSNCT_01_DP6",
            "BSNCT_01_DP7",
            "BSNCT_01_DP8",
            "BSNCT_01_DP9",
            "BSNCT_01_DP10",
            "BSNCT_01_DP11",
            "BSNCT_01_DP12",
            "BSNCT_01_DP13",
            "BSNCT_01_DP14"
        ],
        "EliteData": {
            "chapter": "N_A",
            "initGold": 50,
            "value": "N1"
        },
        "EliteUnlock": [
            "BSNCT_01_S2"
        ],
        "InfData": "",
        "InfUnlock": "",
        "InitAttr": "P_Master_Lv1",
        "InitHero": {
            "HLDNan": "P_Hero_Lv1",
            "JDCZhang": "P_Hero_Lv1",
            "YFZZhu": "P_Hero_Lv1"
        },
        "Master": "PansLab_Player_DFQi",
        "NormalData": {
            "chapter": "N_A",
            "initGold": 50,
            "value": "N1"
        },
        "NormalUnlock": {
            "level": 999
        },
        "Picture": "",
        "Position": 3,
        "SpecialSkill": {
            "cd": 3,
            "desc": "PansLab_BSNCT_01_SpecialSkill",
            "skill": "HeroUp"
        },
        "StoryName": "BSNCT_01_Name",
        "TalentChange": 12,
        "TalentList": [
            "BSNCT_01_Talent1",
            "BSNCT_01_Talent2",
            "BSNCT_01_Talent3",
            "BSNCT_01_Talent4",
            "BSNCT_01_Talent5",
            "BSNCT_01_Talent6",
            "BSNCT_01_Talent7",
            "BSNCT_01_Talent8",
            "BSNCT_01_Talent9",
            "BSNCT_01_Talent10"
        ],
        "TeamBuff": {
            "attr": [
                "PansLab_TeamBuff_1",
                "PansLab_TeamBuff_2",
                "PansLab_TeamBuff_3",
                "PansLab_TeamBuff_4",
                "PansLab_TeamBuff_5"
            ],
            "level": [
                2,
                4,
                6,
                8,
                10
            ],
            "special": []
        }
    },
    "BSNCT_04": {
        "ClueList": [
            "BSNCT_01_C1",
            "BSNCT_01_C2",
            "BSNCT_01_C3",
            "BSNCT_01_C4",
            "BSNCT_01_C5",
            "BSNCT_01_C6",
            "BSNCT_01_C7",
            "BSNCT_01_C8",
            "BSNCT_01_C9",
            "BSNCT_01_C10",
            "BSNCT_01_C11",
            "BSNCT_01_C12",
            "BSNCT_01_C13",
            "BSNCT_01_C14",
            "BSNCT_01_C15",
            "BSNCT_01_C16",
            "BSNCT_01_C17",
            "BSNCT_01_C18",
            "BSNCT_01_C19",
            "BSNCT_01_C20",
            "BSNCT_01_C21",
            "BSNCT_01_C22",
            "BSNCT_01_C23",
            "BSNCT_01_C24",
            "BSNCT_01_C25",
            "BSNCT_01_C26",
            "BSNCT_01_C27",
            "BSNCT_01_C28",
            "BSNCT_01_C29",
            "BSNCT_01_C30",
            "BSNCT_01_C31",
            "BSNCT_01_C32",
            "BSNCT_01_C33",
            "BSNCT_01_C34",
            "BSNCT_01_C35",
            "BSNCT_01_C36",
            "BSNCT_01_C37",
            "BSNCT_01_C38",
            "BSNCT_01_C39",
            "BSNCT_01_C40",
            "BSNCT_01_C41",
            "BSNCT_01_C42",
            "BSNCT_01_C43",
            "BSNCT_01_C44",
            "BSNCT_01_C45",
            "BSNCT_01_C46",
            "BSNCT_01_C47",
            "BSNCT_01_C48",
            "BSNCT_01_C49",
            "BSNCT_01_C50",
            "BSNCT_01_C51",
            "BSNCT_01_C52",
            "BSNCT_01_C53",
            "BSNCT_01_C54",
            "BSNCT_01_C55",
            "BSNCT_01_C56",
            "BSNCT_01_C57",
            "BSNCT_01_C58",
            "BSNCT_01_C59",
            "BSNCT_01_C60",
            "BSNCT_01_C61",
            "BSNCT_01_C62",
            "BSNCT_01_C63",
            "BSNCT_01_C64",
            "BSNCT_01_C65",
            "BSNCT_01_C66",
            "BSNCT_01_C67",
            "BSNCT_01_C68",
            "BSNCT_01_C69",
            "BSNCT_01_C70",
            "BSNCT_01_C71",
            "BSNCT_01_C72",
            "BSNCT_01_C73",
            "BSNCT_01_C74",
            "BSNCT_01_C75",
            "BSNCT_01_C76",
            "BSNCT_01_C77",
            "BSNCT_01_C78",
            "BSNCT_01_C79",
            "BSNCT_01_C80",
            "BSNCT_01_C81",
            "BSNCT_01_C82",
            "BSNCT_01_C83",
            "BSNCT_01_C84",
            "BSNCT_01_C85",
            "BSNCT_01_C86",
            "BSNCT_01_C87",
            "BSNCT_01_C88",
            "BSNCT_01_C89",
            "BSNCT_01_C90",
            "BSNCT_01_C91",
            "BSNCT_01_C92",
            "BSNCT_01_C93",
            "BSNCT_01_C94",
            "BSNCT_01_C95",
            "BSNCT_01_C96",
            "BSNCT_01_C97",
            "BSNCT_01_C98",
            "BSNCT_01_C99",
            "BSNCT_01_C100",
            "BSNCT_01_C101",
            "BSNCT_01_C102",
            "BSNCT_01_C103",
            "BSNCT_01_C104",
            "BSNCT_01_C105",
            "BSNCT_01_C106",
            "BSNCT_01_C107",
            "BSNCT_01_C108",
            "BSNCT_01_C109",
            "BSNCT_01_C110",
            "BSNCT_01_C111",
            "BSNCT_01_C112",
            "BSNCT_01_C113",
            "BSNCT_01_C114",
            "BSNCT_01_C115",
            "BSNCT_01_C116",
            "BSNCT_01_C117",
            "BSNCT_01_C118",
            "BSNCT_01_C119",
            "BSNCT_01_C120"
        ],
        "DPReward": {
            "120": "exp_small",
            "30": "exp_small",
            "60": "exp_small",
            "90": "exp_small"
        },
        "DPTask": [
            "BSNCT_01_DP1",
            "BSNCT_01_DP2",
            "BSNCT_01_DP3",
            "BSNCT_01_DP4",
            "BSNCT_01_DP5",
            "BSNCT_01_DP6",
            "BSNCT_01_DP7",
            "BSNCT_01_DP8",
            "BSNCT_01_DP9",
            "BSNCT_01_DP10",
            "BSNCT_01_DP11",
            "BSNCT_01_DP12",
            "BSNCT_01_DP13",
            "BSNCT_01_DP14"
        ],
        "EliteData": {
            "chapter": "N_A",
            "initGold": 50,
            "value": "N1"
        },
        "EliteUnlock": [
            "BSNCT_01_S2"
        ],
        "InfData": "",
        "InfUnlock": "",
        "InitAttr": "P_Master_Lv1",
        "InitHero": {
            "HLDNan": "P_Hero_Lv1",
            "JDCZhang": "P_Hero_Lv1",
            "YFZZhu": "P_Hero_Lv1"
        },
        "Master": "PansLab_Player_DFQi",
        "NormalData": {
            "chapter": "N_A",
            "initGold": 50,
            "value": "N1"
        },
        "NormalUnlock": {
            "level": 999
        },
        "Picture": "",
        "Position": 4,
        "SpecialSkill": {
            "cd": 3,
            "desc": "PansLab_BSNCT_01_SpecialSkill",
            "skill": "HeroUp"
        },
        "StoryName": "BSNCT_01_Name",
        "TalentChange": 12,
        "TalentList": [
            "BSNCT_01_Talent1",
            "BSNCT_01_Talent2",
            "BSNCT_01_Talent3",
            "BSNCT_01_Talent4",
            "BSNCT_01_Talent5",
            "BSNCT_01_Talent6",
            "BSNCT_01_Talent7",
            "BSNCT_01_Talent8",
            "BSNCT_01_Talent9",
            "BSNCT_01_Talent10"
        ],
        "TeamBuff": {
            "attr": [
                "PansLab_TeamBuff_1",
                "PansLab_TeamBuff_2",
                "PansLab_TeamBuff_3",
                "PansLab_TeamBuff_4",
                "PansLab_TeamBuff_5"
            ],
            "level": [
                2,
                4,
                6,
                8,
                10
            ],
            "special": []
        }
    },
    "BSNCT_05": {
        "ClueList": [
            "BSNCT_01_C1",
            "BSNCT_01_C2",
            "BSNCT_01_C3",
            "BSNCT_01_C4",
            "BSNCT_01_C5",
            "BSNCT_01_C6",
            "BSNCT_01_C7",
            "BSNCT_01_C8",
            "BSNCT_01_C9",
            "BSNCT_01_C10",
            "BSNCT_01_C11",
            "BSNCT_01_C12",
            "BSNCT_01_C13",
            "BSNCT_01_C14",
            "BSNCT_01_C15",
            "BSNCT_01_C16",
            "BSNCT_01_C17",
            "BSNCT_01_C18",
            "BSNCT_01_C19",
            "BSNCT_01_C20",
            "BSNCT_01_C21",
            "BSNCT_01_C22",
            "BSNCT_01_C23",
            "BSNCT_01_C24",
            "BSNCT_01_C25",
            "BSNCT_01_C26",
            "BSNCT_01_C27",
            "BSNCT_01_C28",
            "BSNCT_01_C29",
            "BSNCT_01_C30",
            "BSNCT_01_C31",
            "BSNCT_01_C32",
            "BSNCT_01_C33",
            "BSNCT_01_C34",
            "BSNCT_01_C35",
            "BSNCT_01_C36",
            "BSNCT_01_C37",
            "BSNCT_01_C38",
            "BSNCT_01_C39",
            "BSNCT_01_C40",
            "BSNCT_01_C41",
            "BSNCT_01_C42",
            "BSNCT_01_C43",
            "BSNCT_01_C44",
            "BSNCT_01_C45",
            "BSNCT_01_C46",
            "BSNCT_01_C47",
            "BSNCT_01_C48",
            "BSNCT_01_C49",
            "BSNCT_01_C50",
            "BSNCT_01_C51",
            "BSNCT_01_C52",
            "BSNCT_01_C53",
            "BSNCT_01_C54",
            "BSNCT_01_C55",
            "BSNCT_01_C56",
            "BSNCT_01_C57",
            "BSNCT_01_C58",
            "BSNCT_01_C59",
            "BSNCT_01_C60",
            "BSNCT_01_C61",
            "BSNCT_01_C62",
            "BSNCT_01_C63",
            "BSNCT_01_C64",
            "BSNCT_01_C65",
            "BSNCT_01_C66",
            "BSNCT_01_C67",
            "BSNCT_01_C68",
            "BSNCT_01_C69",
            "BSNCT_01_C70",
            "BSNCT_01_C71",
            "BSNCT_01_C72",
            "BSNCT_01_C73",
            "BSNCT_01_C74",
            "BSNCT_01_C75",
            "BSNCT_01_C76",
            "BSNCT_01_C77",
            "BSNCT_01_C78",
            "BSNCT_01_C79",
            "BSNCT_01_C80",
            "BSNCT_01_C81",
            "BSNCT_01_C82",
            "BSNCT_01_C83",
            "BSNCT_01_C84",
            "BSNCT_01_C85",
            "BSNCT_01_C86",
            "BSNCT_01_C87",
            "BSNCT_01_C88",
            "BSNCT_01_C89",
            "BSNCT_01_C90",
            "BSNCT_01_C91",
            "BSNCT_01_C92",
            "BSNCT_01_C93",
            "BSNCT_01_C94",
            "BSNCT_01_C95",
            "BSNCT_01_C96",
            "BSNCT_01_C97",
            "BSNCT_01_C98",
            "BSNCT_01_C99",
            "BSNCT_01_C100",
            "BSNCT_01_C101",
            "BSNCT_01_C102",
            "BSNCT_01_C103",
            "BSNCT_01_C104",
            "BSNCT_01_C105",
            "BSNCT_01_C106",
            "BSNCT_01_C107",
            "BSNCT_01_C108",
            "BSNCT_01_C109",
            "BSNCT_01_C110",
            "BSNCT_01_C111",
            "BSNCT_01_C112",
            "BSNCT_01_C113",
            "BSNCT_01_C114",
            "BSNCT_01_C115",
            "BSNCT_01_C116",
            "BSNCT_01_C117",
            "BSNCT_01_C118",
            "BSNCT_01_C119",
            "BSNCT_01_C120"
        ],
        "DPReward": {
            "120": "exp_small",
            "30": "exp_small",
            "60": "exp_small",
            "90": "exp_small"
        },
        "DPTask": [
            "BSNCT_01_DP1",
            "BSNCT_01_DP2",
            "BSNCT_01_DP3",
            "BSNCT_01_DP4",
            "BSNCT_01_DP5",
            "BSNCT_01_DP6",
            "BSNCT_01_DP7",
            "BSNCT_01_DP8",
            "BSNCT_01_DP9",
            "BSNCT_01_DP10",
            "BSNCT_01_DP11",
            "BSNCT_01_DP12",
            "BSNCT_01_DP13",
            "BSNCT_01_DP14"
        ],
        "EliteData": {
            "chapter": "N_A",
            "initGold": 50,
            "value": "N1"
        },
        "EliteUnlock": [
            "BSNCT_01_S2"
        ],
        "InfData": "",
        "InfUnlock": "",
        "InitAttr": "P_Master_Lv1",
        "InitHero": {
            "HLDNan": "P_Hero_Lv1",
            "JDCZhang": "P_Hero_Lv1",
            "YFZZhu": "P_Hero_Lv1"
        },
        "Master": "PansLab_Player_DFQi",
        "NormalData": {
            "chapter": "N_A",
            "initGold": 50,
            "value": "N1"
        },
        "NormalUnlock": {
            "level": 999
        },
        "Picture": "",
        "Position": 5,
        "SpecialSkill": {
            "cd": 3,
            "desc": "PansLab_BSNCT_01_SpecialSkill",
            "skill": "HeroUp"
        },
        "StoryName": "BSNCT_01_Name",
        "TalentChange": 12,
        "TalentList": [
            "BSNCT_01_Talent1",
            "BSNCT_01_Talent2",
            "BSNCT_01_Talent3",
            "BSNCT_01_Talent4",
            "BSNCT_01_Talent5",
            "BSNCT_01_Talent6",
            "BSNCT_01_Talent7",
            "BSNCT_01_Talent8",
            "BSNCT_01_Talent9",
            "BSNCT_01_Talent10"
        ],
        "TeamBuff": {
            "attr": [
                "PansLab_TeamBuff_1",
                "PansLab_TeamBuff_2",
                "PansLab_TeamBuff_3",
                "PansLab_TeamBuff_4",
                "PansLab_TeamBuff_5"
            ],
            "level": [
                2,
                4,
                6,
                8,
                10
            ],
            "special": []
        }
    },
    "BSNCT_06": {
        "ClueList": [
            "BSNCT_01_C1",
            "BSNCT_01_C2",
            "BSNCT_01_C3",
            "BSNCT_01_C4",
            "BSNCT_01_C5",
            "BSNCT_01_C6",
            "BSNCT_01_C7",
            "BSNCT_01_C8",
            "BSNCT_01_C9",
            "BSNCT_01_C10",
            "BSNCT_01_C11",
            "BSNCT_01_C12",
            "BSNCT_01_C13",
            "BSNCT_01_C14",
            "BSNCT_01_C15",
            "BSNCT_01_C16",
            "BSNCT_01_C17",
            "BSNCT_01_C18",
            "BSNCT_01_C19",
            "BSNCT_01_C20",
            "BSNCT_01_C21",
            "BSNCT_01_C22",
            "BSNCT_01_C23",
            "BSNCT_01_C24",
            "BSNCT_01_C25",
            "BSNCT_01_C26",
            "BSNCT_01_C27",
            "BSNCT_01_C28",
            "BSNCT_01_C29",
            "BSNCT_01_C30",
            "BSNCT_01_C31",
            "BSNCT_01_C32",
            "BSNCT_01_C33",
            "BSNCT_01_C34",
            "BSNCT_01_C35",
            "BSNCT_01_C36",
            "BSNCT_01_C37",
            "BSNCT_01_C38",
            "BSNCT_01_C39",
            "BSNCT_01_C40",
            "BSNCT_01_C41",
            "BSNCT_01_C42",
            "BSNCT_01_C43",
            "BSNCT_01_C44",
            "BSNCT_01_C45",
            "BSNCT_01_C46",
            "BSNCT_01_C47",
            "BSNCT_01_C48",
            "BSNCT_01_C49",
            "BSNCT_01_C50",
            "BSNCT_01_C51",
            "BSNCT_01_C52",
            "BSNCT_01_C53",
            "BSNCT_01_C54",
            "BSNCT_01_C55",
            "BSNCT_01_C56",
            "BSNCT_01_C57",
            "BSNCT_01_C58",
            "BSNCT_01_C59",
            "BSNCT_01_C60",
            "BSNCT_01_C61",
            "BSNCT_01_C62",
            "BSNCT_01_C63",
            "BSNCT_01_C64",
            "BSNCT_01_C65",
            "BSNCT_01_C66",
            "BSNCT_01_C67",
            "BSNCT_01_C68",
            "BSNCT_01_C69",
            "BSNCT_01_C70",
            "BSNCT_01_C71",
            "BSNCT_01_C72",
            "BSNCT_01_C73",
            "BSNCT_01_C74",
            "BSNCT_01_C75",
            "BSNCT_01_C76",
            "BSNCT_01_C77",
            "BSNCT_01_C78",
            "BSNCT_01_C79",
            "BSNCT_01_C80",
            "BSNCT_01_C81",
            "BSNCT_01_C82",
            "BSNCT_01_C83",
            "BSNCT_01_C84",
            "BSNCT_01_C85",
            "BSNCT_01_C86",
            "BSNCT_01_C87",
            "BSNCT_01_C88",
            "BSNCT_01_C89",
            "BSNCT_01_C90",
            "BSNCT_01_C91",
            "BSNCT_01_C92",
            "BSNCT_01_C93",
            "BSNCT_01_C94",
            "BSNCT_01_C95",
            "BSNCT_01_C96",
            "BSNCT_01_C97",
            "BSNCT_01_C98",
            "BSNCT_01_C99",
            "BSNCT_01_C100",
            "BSNCT_01_C101",
            "BSNCT_01_C102",
            "BSNCT_01_C103",
            "BSNCT_01_C104",
            "BSNCT_01_C105",
            "BSNCT_01_C106",
            "BSNCT_01_C107",
            "BSNCT_01_C108",
            "BSNCT_01_C109",
            "BSNCT_01_C110",
            "BSNCT_01_C111",
            "BSNCT_01_C112",
            "BSNCT_01_C113",
            "BSNCT_01_C114",
            "BSNCT_01_C115",
            "BSNCT_01_C116",
            "BSNCT_01_C117",
            "BSNCT_01_C118",
            "BSNCT_01_C119",
            "BSNCT_01_C120"
        ],
        "DPReward": {
            "120": "exp_small",
            "30": "exp_small",
            "60": "exp_small",
            "90": "exp_small"
        },
        "DPTask": [
            "BSNCT_01_DP1",
            "BSNCT_01_DP2",
            "BSNCT_01_DP3",
            "BSNCT_01_DP4",
            "BSNCT_01_DP5",
            "BSNCT_01_DP6",
            "BSNCT_01_DP7",
            "BSNCT_01_DP8",
            "BSNCT_01_DP9",
            "BSNCT_01_DP10",
            "BSNCT_01_DP11",
            "BSNCT_01_DP12",
            "BSNCT_01_DP13",
            "BSNCT_01_DP14"
        ],
        "EliteData": {
            "chapter": "N_A",
            "initGold": 50,
            "value": "N1"
        },
        "EliteUnlock": [
            "BSNCT_01_S2"
        ],
        "InfData": "",
        "InfUnlock": "",
        "InitAttr": "P_Master_Lv1",
        "InitHero": {
            "HLDNan": "P_Hero_Lv1",
            "JDCZhang": "P_Hero_Lv1",
            "YFZZhu": "P_Hero_Lv1"
        },
        "Master": "PansLab_Player_DFQi",
        "NormalData": {
            "chapter": "N_A",
            "initGold": 50,
            "value": "N1"
        },
        "NormalUnlock": {
            "level": 999
        },
        "Picture": "",
        "Position": 6,
        "SpecialSkill": {
            "cd": 3,
            "desc": "PansLab_BSNCT_01_SpecialSkill",
            "skill": "HeroUp"
        },
        "StoryName": "BSNCT_01_Name",
        "TalentChange": 12,
        "TalentList": [
            "BSNCT_01_Talent1",
            "BSNCT_01_Talent2",
            "BSNCT_01_Talent3",
            "BSNCT_01_Talent4",
            "BSNCT_01_Talent5",
            "BSNCT_01_Talent6",
            "BSNCT_01_Talent7",
            "BSNCT_01_Talent8",
            "BSNCT_01_Talent9",
            "BSNCT_01_Talent10"
        ],
        "TeamBuff": {
            "attr": [
                "PansLab_TeamBuff_1",
                "PansLab_TeamBuff_2",
                "PansLab_TeamBuff_3",
                "PansLab_TeamBuff_4",
                "PansLab_TeamBuff_5"
            ],
            "level": [
                2,
                4,
                6,
                8,
                10
            ],
            "special": []
        }
    }
}